genstr/__init__.py
genstr/utils.py
genstr-0.1.0.dist-info/METADATA
genstr-0.1.0.dist-info/WHEEL
genstr-0.1.0.dist-info/licenses/LICENSE
genstr-0.1.0.dist-info/RECORD
