Metadata-Version: 2.4
Name: genstr
Version: 0.1.0
Summary: 按指定规则生成字符串。
Project-URL: Homepage, https://git.jetsung.com/idev/pygenstr
Project-URL: Documentation, https://framagit.org/idev/pygenstr
Project-URL: Repository, https://framagit.org/idev/pygenstr.git
Author-email: Jetsung Chan <jetsungchan@gmail.com>
License: Apache-2.0
License-File: LICENSE
Keywords: generator,string
Requires-Python: >=3.10
